treelib/__init__.py
treelib/exceptions.py
treelib/misc.py
treelib/node.py
treelib/tree.py
treelib-1.7.0.dist-info/AUTHORS
treelib-1.7.0.dist-info/LICENSE
treelib-1.7.0.dist-info/METADATA
treelib-1.7.0.dist-info/WHEEL
treelib-1.7.0.dist-info/top_level.txt
treelib-1.7.0.dist-info/RECORD
